pyzonda
